samplepackage1/__init__.py
samplepackage1/test.py
srikanth1234567-0.0.1.dist-info/LICENSE.txt
srikanth1234567-0.0.1.dist-info/METADATA
srikanth1234567-0.0.1.dist-info/WHEEL
srikanth1234567-0.0.1.dist-info/top_level.txt
srikanth1234567-0.0.1.dist-info/RECORD
